pisten/__init__.py
pisten/__main__.py
pisten/pisten.py
pisten-0.2.1.dist-info/LICENSE
pisten-0.2.1.dist-info/METADATA
pisten-0.2.1.dist-info/WHEEL
pisten-0.2.1.dist-info/entry_points.txt
pisten-0.2.1.dist-info/top_level.txt
pisten-0.2.1.dist-info/RECORD
