Metadata-Version: 2.1
Name: pisten
Version: 0.2.1
Summary: A simple magic packet forwarder
Home-page: https://github.com/davidpratt512/pisten
Author: David Pratt
Author-email: davidpratt512@gmail.com
License: MIT
Keywords: wakeonlan wake-on-lan port-forwarding magic-packet
Platform: UNKNOWN
Classifier: Development Status :: 4 - Beta
Classifier: Intended Audience :: System Administrators
Classifier: Topic :: System :: Networking
Classifier: Programming Language :: Python :: 3 :: Only
Classifier: License :: OSI Approved :: MIT License
Classifier: Operating System :: OS Independent
Requires-Python: >=3
